pendulum/__init__.py
pendulum/__version__.py
pendulum/_helpers.py
pendulum/_pendulum.pyi
pendulum/constants.py
pendulum/date.py
pendulum/datetime.py
pendulum/day.py
pendulum/duration.py
pendulum/exceptions.py
pendulum/formatting/__init__.py
pendulum/formatting/difference_formatter.py
pendulum/formatting/formatter.py
pendulum/helpers.py
pendulum/interval.py
pendulum/locales/__init__.py
pendulum/locales/cs/__init__.py
pendulum/locales/cs/custom.py
pendulum/locales/cs/locale.py
pendulum/locales/da/__init__.py
pendulum/locales/da/custom.py
pendulum/locales/da/locale.py
pendulum/locales/de/__init__.py
pendulum/locales/de/custom.py
pendulum/locales/de/locale.py
pendulum/locales/en/__init__.py
pendulum/locales/en/custom.py
pendulum/locales/en/locale.py
pendulum/locales/en_gb/__init__.py
pendulum/locales/en_gb/custom.py
pendulum/locales/en_gb/locale.py
pendulum/locales/en_us/__init__.py
pendulum/locales/en_us/custom.py
pendulum/locales/en_us/locale.py
pendulum/locales/es/__init__.py
pendulum/locales/es/custom.py
pendulum/locales/es/locale.py
pendulum/locales/fa/__init__.py
pendulum/locales/fa/custom.py
pendulum/locales/fa/locale.py
pendulum/locales/fo/__init__.py
pendulum/locales/fo/custom.py
pendulum/locales/fo/locale.py
pendulum/locales/fr/__init__.py
pendulum/locales/fr/custom.py
pendulum/locales/fr/locale.py
pendulum/locales/he/__init__.py
pendulum/locales/he/custom.py
pendulum/locales/he/locale.py
pendulum/locales/id/__init__.py
pendulum/locales/id/custom.py
pendulum/locales/id/locale.py
pendulum/locales/it/__init__.py
pendulum/locales/it/custom.py
pendulum/locales/it/locale.py
pendulum/locales/ja/__init__.py
pendulum/locales/ja/custom.py
pendulum/locales/ja/locale.py
pendulum/locales/ko/__init__.py
pendulum/locales/ko/custom.py
pendulum/locales/ko/locale.py
pendulum/locales/locale.py
pendulum/locales/lt/__init__.py
pendulum/locales/lt/custom.py
pendulum/locales/lt/locale.py
pendulum/locales/nb/__init__.py
pendulum/locales/nb/custom.py
pendulum/locales/nb/locale.py
dlt_pendulum-3.0.2.dist-info/LICENSE
dlt_pendulum-3.0.2.dist-info/METADATA
dlt_pendulum-3.0.2.dist-info/WHEEL
dlt_pendulum-3.0.2.dist-info/RECORD
