Metadata-Version: 2.1
Name: dlt-pendulum
Version: 3.0.2
Summary: Python datetimes made easy
Home-page: https://pendulum.eustace.io
License: MIT
Keywords: datetime,date,time
Author: Sébastien Eustace
Author-email: sebastien@eustace.io
Requires-Python: >=3.9
Classifier: License :: OSI Approved :: MIT License
Classifier: Programming Language :: Python :: 3
Classifier: Programming Language :: Python :: 3.9
Classifier: Programming Language :: Python :: 3.10
Classifier: Programming Language :: Python :: 3.11
Classifier: Programming Language :: Python :: 3.12
Classifier: Programming Language :: Python :: 3.13
Provides-Extra: test
Requires-Dist: cffi (>=1.17)
Requires-Dist: python-dateutil (>=2.6)
Requires-Dist: tzdata (>=2020.1)
Project-URL: Documentation, https://pendulum.eustace.io/docs
Project-URL: Repository, https://github.com/sdispater/pendulum
